ghai/__init__.py
ghai/cli.py
ghai/github_api.py
ghai/llm_api.py
ghai/commands/__init__.py
ghai/commands/explain_issue.py
ghai/commands/keys.py
ghai/commands/progress_update.py
ghai/commands/snippet_update.py
ghai/prompts/__init__.py
ghai/prompts/explain_issue_prompt.md
ghai/prompts/initiative_prompt.md
ghai/prompts/snippet_prompt.md
ghai/types/github_api_types.py
ghai/util/__init__.py
ghai/util/key_util.py
githai-0.1.1.dist-info/METADATA
githai-0.1.1.dist-info/WHEEL
githai-0.1.1.dist-info/entry_points.txt
githai-0.1.1.dist-info/top_level.txt
githai-0.1.1.dist-info/RECORD
